LICENSE
README.md
pibooth_flashled.py
setup.py
pibooth_flashled.egg-info/PKG-INFO
pibooth_flashled.egg-info/SOURCES.txt
pibooth_flashled.egg-info/dependency_links.txt
pibooth_flashled.egg-info/entry_points.txt
pibooth_flashled.egg-info/not-zip-safe
pibooth_flashled.egg-info/requires.txt
pibooth_flashled.egg-info/top_level.txt