Metadata-Version: 2.1
Name: pibooth-flashled
Version: 1.0.0
Summary: UNKNOWN
Home-page: https://github.com/grenagit/pibooth-flashled
Author: Grena
Author-email: grena+pibooth@grenabox.fr
License: MIT license
Download-URL: https://github.com/grenagit/pibooth-flashled/archive/1.0.0.tar.gz
Keywords: Raspberry Pi,camera,photobooth,led
Platform: unix
Platform: linux
Classifier: Development Status :: 5 - Production/Stable
Classifier: Environment :: Other Environment
Classifier: Intended Audience :: Developers
Classifier: Intended Audience :: End Users/Desktop
Classifier: License :: OSI Approved :: MIT License
Classifier: Operating System :: POSIX :: Linux
Classifier: Programming Language :: Python :: 3.6
Classifier: Programming Language :: Python :: 3.7
Classifier: Programming Language :: Python :: 3.8
Classifier: Programming Language :: Python :: 3.9
Classifier: Natural Language :: English
Classifier: Topic :: Multimedia :: Graphics :: Capture :: Digital Camera
License-File: LICENSE
